odoo/addons/account_move_line_landed_cost_info/README.rst
odoo/addons/account_move_line_landed_cost_info/__init__.py
odoo/addons/account_move_line_landed_cost_info/__manifest__.py
odoo/addons/account_move_line_landed_cost_info/hooks.py
odoo/addons/account_move_line_landed_cost_info/i18n/account_move_line_landed_cost_info.pot
odoo/addons/account_move_line_landed_cost_info/i18n/es.po
odoo/addons/account_move_line_landed_cost_info/i18n/it.po
odoo/addons/account_move_line_landed_cost_info/models/__init__.py
odoo/addons/account_move_line_landed_cost_info/models/account_move.py
odoo/addons/account_move_line_landed_cost_info/models/stock_valuation_adjustment_lines.py
odoo/addons/account_move_line_landed_cost_info/readme/CONTRIBUTORS.rst
odoo/addons/account_move_line_landed_cost_info/readme/DESCRIPTION.rst
odoo/addons/account_move_line_landed_cost_info/readme/USAGE.rst
odoo/addons/account_move_line_landed_cost_info/static/description/icon.png
odoo/addons/account_move_line_landed_cost_info/static/description/index.html
odoo/addons/account_move_line_landed_cost_info/views/account_move_view.xml
odoo14_addon_account_move_line_landed_cost_info-14.0.1.0.1.dev7.dist-info/METADATA
odoo14_addon_account_move_line_landed_cost_info-14.0.1.0.1.dev7.dist-info/WHEEL
odoo14_addon_account_move_line_landed_cost_info-14.0.1.0.1.dev7.dist-info/top_level.txt
odoo14_addon_account_move_line_landed_cost_info-14.0.1.0.1.dev7.dist-info/RECORD
